setup.cfg
setup.py
distributions/Binomialdistribution.py
distributions/Gaussiandistribution.py
distributions/Generaldistribution.py
distributions/__init__.py
prob_distrok.egg-info/PKG-INFO
prob_distrok.egg-info/SOURCES.txt
prob_distrok.egg-info/dependency_links.txt
prob_distrok.egg-info/not-zip-safe
prob_distrok.egg-info/top_level.txt