Metadata-Version: 1.0
Name: prob-distrok
Version: 0.1
Summary: Gaussian distributions
Home-page: UNKNOWN
Author: Godfrey Tutu
Author-email: godfrey_tutu@yahoo.com
License: UNKNOWN
Platform: UNKNOWN
